jupyterlab_git_newland/__init__.py
jupyterlab_git_newland/_version.py
jupyterlab_git_newland/git.py
jupyterlab_git_newland/handlers.py
jupyterlab_git_newland/log.py
jupyterlab_git_newland/labextension/package.json
jupyterlab_git_newland/labextension/schemas/@jupyterlab/git/package.json.orig
jupyterlab_git_newland/labextension/schemas/@jupyterlab/git/plugin.json
jupyterlab_git_newland/labextension/static/114.58bfd46b7e255fab2493.js
jupyterlab_git_newland/labextension/static/172.aeca84bf05404145e465.js
jupyterlab_git_newland/labextension/static/266.a72bfd329f30526903f4.js
jupyterlab_git_newland/labextension/static/27.f4e05badfaa92dc098f1.js
jupyterlab_git_newland/labextension/static/392.1a1ef0d661b4701fd265.js
jupyterlab_git_newland/labextension/static/534.4115814409bff72c2830.js
jupyterlab_git_newland/labextension/static/554.dec85e1f2f69ea0d52b1.js
jupyterlab_git_newland/labextension/static/566.a99c1a305361be173e6a.js
jupyterlab_git_newland/labextension/static/566.a99c1a305361be173e6a.js.LICENSE.txt
jupyterlab_git_newland/labextension/static/703.8591dc5c74e98194e681.js
jupyterlab_git_newland/labextension/static/728.b0cda115c0ba87a60523.js
jupyterlab_git_newland/labextension/static/813.42f36bdcedefa7f4f6db.js
jupyterlab_git_newland/labextension/static/912.0f408c5ed17a59945ccf.js
jupyterlab_git_newland/labextension/static/912.0f408c5ed17a59945ccf.js.LICENSE.txt
jupyterlab_git_newland/labextension/static/remoteEntry.8a00a6d4da8ad17d9cf5.js
jupyterlab_git_newland/labextension/static/style.js
jupyterlab_git_newland/tests/__init__.py
jupyterlab_git_newland/tests/conftest.py
jupyterlab_git_newland/tests/test_branch.py
jupyterlab_git_newland/tests/test_clone.py
jupyterlab_git_newland/tests/test_config.py
jupyterlab_git_newland/tests/test_detailed_log.py
jupyterlab_git_newland/tests/test_diff.py
jupyterlab_git_newland/tests/test_execute.py
jupyterlab_git_newland/tests/test_handlers.py
jupyterlab_git_newland/tests/test_hybridcontents.py
jupyterlab_git_newland-0.0.1.dist-info/LICENSE
jupyterlab_git_newland-0.0.1.dist-info/METADATA
jupyterlab_git_newland-0.0.1.dist-info/WHEEL
jupyterlab_git_newland-0.0.1.dist-info/top_level.txt
jupyterlab_git_newland-0.0.1.dist-info/RECORD
