Metadata-Version: 2.1
Name: jupyterlab-git-newland
Version: 0.0.1
Summary: A JupyterLab extension for version control using git
Home-page: https://github.com/jupyterlab/jupyterlab-git.git
Author: Jupyter Development Team
License: BSD-3-Clause
Keywords: Jupyter,JupyterLab,JupyterLab3,Git
Platform: Linux
Platform: Mac OS X
Platform: Windows
Classifier: Intended Audience :: Developers
Classifier: Intended Audience :: Science/Research
Classifier: License :: OSI Approved :: BSD License
Classifier: Programming Language :: Python
Classifier: Programming Language :: Python :: 3
Classifier: Programming Language :: Python :: 3.6
Classifier: Programming Language :: Python :: 3.7
Classifier: Programming Language :: Python :: 3.8
Classifier: Programming Language :: Python :: 3.9
Classifier: Framework :: Jupyter
Requires-Python: >=3.6,<4
License-File: LICENSE
Requires-Dist: jupyter-server
Requires-Dist: nbdime (~=3.1)
Requires-Dist: nbformat
Requires-Dist: packaging
Requires-Dist: pexpect
Provides-Extra: dev
Requires-Dist: black ; extra == 'dev'
Requires-Dist: coverage ; extra == 'dev'
Requires-Dist: jupyter-packaging (~=0.7.9) ; extra == 'dev'
Requires-Dist: jupyterlab (~=3.0) ; extra == 'dev'
Requires-Dist: pre-commit ; extra == 'dev'
Requires-Dist: pytest ; extra == 'dev'
Requires-Dist: pytest-asyncio ; extra == 'dev'
Requires-Dist: pytest-cov ; extra == 'dev'
Requires-Dist: pytest-tornasync ; extra == 'dev'
Provides-Extra: tests
Requires-Dist: hybridcontents ; extra == 'tests'
